abromics/__init__.py
abromics/__main__.py
abromics/cli.py
abromics/client.py
abromics/exceptions.py
abromics/auth/__init__.py
abromics/auth/api_key.py
abromics/batch/__init__.py
abromics/batch/batch_uploader.py
abromics/batch/processor.py
abromics/batch/tsv_processor.py
abromics/models/__init__.py
abromics/models/experiment.py
abromics/models/project.py
abromics/models/sample.py
abromics/models/template.py
abromics/upload/__init__.py
abromics/upload/tus_client.py
abromics/utils/__init__.py
abromics/utils/constants.py
abromics_library-1.0.6.dist-info/METADATA
abromics_library-1.0.6.dist-info/WHEEL
abromics_library-1.0.6.dist-info/entry_points.txt
abromics_library-1.0.6.dist-info/top_level.txt
abromics_library-1.0.6.dist-info/RECORD
