Metadata-Version: 2.4
Name: abromics-library
Version: 1.0.6
Summary: Lightweight Python SDK for ABRomics API
Author-email: ABRomics Team <abromics-team@groupes.france-bioinformatique.fr>
License: MIT
Project-URL: Homepage, https://gitlab.com/ifb-elixirfr/abromics/abromics-analysis
Project-URL: Repository, https://gitlab.com/ifb-elixirfr/abromics/abromics-analysis
Classifier: Development Status :: 5 - Production/Stable
Classifier: Intended Audience :: Science/Research
Classifier: Operating System :: OS Independent
Classifier: Programming Language :: Python :: 3
Classifier: Programming Language :: Python :: 3.8
Classifier: Programming Language :: Python :: 3.9
Classifier: Programming Language :: Python :: 3.10
Classifier: Programming Language :: Python :: 3.11
Classifier: Programming Language :: Python :: 3.12
Classifier: Topic :: Scientific/Engineering :: Bio-Informatics
Requires-Python: >=3.8
Requires-Dist: requests>=2.28.0
Requires-Dist: click>=8.0.0
Requires-Dist: pydantic>=1.10.0
Provides-Extra: dev
Requires-Dist: pytest>=6.0; extra == "dev"
Requires-Dist: pytest-cov>=2.0; extra == "dev"
Requires-Dist: black>=21.0; extra == "dev"
Requires-Dist: flake8>=3.8; extra == "dev"
Requires-Dist: mypy>=0.800; extra == "dev"
Provides-Extra: upload
Requires-Dist: tuspy>=0.2.4; extra == "upload"
